noteplay/__init__.py
noteplay/tianchi/__init__.py
noteplay/tianchi/531803/__init__.py
noteplay/tianchi/531803/core.py
noteplay-0.4.6.dist-info/METADATA
noteplay-0.4.6.dist-info/WHEEL
noteplay-0.4.6.dist-info/top_level.txt
noteplay-0.4.6.dist-info/RECORD
