Metadata-Version: 2.1
Name: noteplay
Version: 0.4.6
Summary: noteplay
Home-page: https://github.com/1007530194
Author: niuliangtao
Author-email: 1007530194@qq.com
License: UNKNOWN
Platform: UNKNOWN
Requires-Dist: notedrive
